JavPy/__init__.py
JavPy/develop.py
JavPy/serve.py
JavPy/app/__init__.py
JavPy/app/tgbot/__init__.py
JavPy/app/tgbot/reply.py
JavPy/app/tgbot/server.py
JavPy/app/webfe/build/asset-manifest.json
JavPy/app/webfe/build/favicon.ico
JavPy/app/webfe/build/index.html
JavPy/app/webfe/build/manifest.json
JavPy/app/webfe/build/precache-manifest.36e22ff21e402cdbf1f7523f3042b7c4.js
JavPy/app/webfe/build/robots.txt
JavPy/app/webfe/build/service-worker.js
JavPy/app/webfe/build/static/css/2.a33d7f97.chunk.css
JavPy/app/webfe/build/static/css/2.a33d7f97.chunk.css.map
JavPy/app/webfe/build/static/css/main.12301873.chunk.css
JavPy/app/webfe/build/static/css/main.12301873.chunk.css.map
JavPy/app/webfe/build/static/js/2.61a51e60.chunk.js
JavPy/app/webfe/build/static/js/2.61a51e60.chunk.js.LICENSE.txt
JavPy/app/webfe/build/static/js/2.61a51e60.chunk.js.map
JavPy/app/webfe/build/static/js/main.d70974a3.chunk.js
JavPy/app/webfe/build/static/js/main.d70974a3.chunk.js.map
JavPy/app/webfe/build/static/js/runtime-main.39a99049.js
JavPy/app/webfe/build/static/js/runtime-main.39a99049.js.map
JavPy/app/webserver/__init__.py
JavPy/app/webserver/app.py
JavPy/download/__init__.py
JavPy/download/download.py
JavPy/embed/BaseEmbed.py
JavPy/embed/__init__.py
JavPy/embed/avgle.py
JavPy/embed/fembed.py
JavPy/embed/fvs_io.py
JavPy/embed/hydrax_net.py
JavPy/embed/javcl_me.py
JavPy/embed/openload.py
JavPy/embed/playfinder_xyz.py
JavPy/embed/smartshare_tv.py
JavPy/embed/xfantasy_tv.py
JavPy/embed/youav_com.py
JavPy/functions/__init__.py
JavPy/functions/actress_info.py
JavPy/functions/actress_translate.py
JavPy/functions/ambiguous_search.py
JavPy/functions/brief.py
JavPy/functions/datastructure.py
JavPy/functions/history_names.py
JavPy/functions/magnet.py
JavPy/functions/new.py
JavPy/functions/search_by_actress.py
JavPy/functions/search_by_code.py
JavPy/functions/sources.py
JavPy/functions/tags.py
JavPy/sources/BaseSource.py
JavPy/sources/__init__.py
JavPy/sources/avgle_com.py
JavPy-0.6.37.dist-info/LICENSE
JavPy-0.6.37.dist-info/METADATA
JavPy-0.6.37.dist-info/WHEEL
JavPy-0.6.37.dist-info/entry_points.txt
JavPy-0.6.37.dist-info/top_level.txt
JavPy-0.6.37.dist-info/RECORD
