Metadata-Version: 2.1
Name: JavPy
Version: 0.6.37
Summary: Watch and explore Japanese AV in a Pythonic way!
Home-page: https://github.com/TheodoreKrypton/JavPy
Author: Theodore Krypton
Author-email: wheatcarrier@gmail.com
License: Apache-2.0 License
Platform: UNKNOWN
Classifier: License :: OSI Approved :: Apache Software License
Classifier: Programming Language :: Python :: 3.5
Classifier: Programming Language :: Python :: 3.6
Classifier: Programming Language :: Python :: 3.7
Classifier: Programming Language :: Python :: 3.8
Requires-Python: >=3.5
Requires-Dist: packaging
Requires-Dist: setuptools
Requires-Dist: requests
Requires-Dist: python-telegram-bot
Requires-Dist: bs4
Requires-Dist: urllib3
Requires-Dist: Flask
Requires-Dist: flask-cors
Requires-Dist: lxml
Requires-Dist: ipaddr
Requires-Dist: pycryptodome
Requires-Dist: cloudscraper
Requires-Dist: pysocks
Requires-Dist: pebble
